MANIFEST.in
README.rst
setup.py
tgext/__init__.py
tgext.webassets.egg-info/PKG-INFO
tgext.webassets.egg-info/SOURCES.txt
tgext.webassets.egg-info/dependency_links.txt
tgext.webassets.egg-info/entry_points.txt
tgext.webassets.egg-info/namespace_packages.txt
tgext.webassets.egg-info/not-zip-safe
tgext.webassets.egg-info/requires.txt
tgext.webassets.egg-info/top_level.txt
tgext/webassets/__init__.py
tgext/webassets/setup_extension.py