Metadata-Version: 1.0
Name: tgext.webassets
Version: 0.0.1
Summary: assets management extension for TurboGears2
Home-page: https://github.com/amol-/tgext.webassets
Author: Alessandro Molina
Author-email: alessandro.molina@axant.it
License: MIT
Keywords: turbogears2.extension
Platform: UNKNOWN
